{"lines":[{"value":" se yon matematisyen nan dyaspora afriken.","name":"Haitian","natural":"Kreyòl ayisyen","classification":"ht"},{"value":"*Dat enpòtan yo","name":"Haitian","natural":"Kreyòl ayisyen","classification":"ht"},{"value":"*Sa li fè, piblikasyon li nan domèn konesans matematik li","name":"Haitian","natural":"Kreyòl ayisyen","classification":"ht"},{"value":"*Referans pou konnen plis anlè moun sa a","name":"Haitian","natural":"Kreyòl ayisyen","classification":"ht"},{"value":" se yon matematisyen ameriken.","name":"Haitian","natural":"Kreyòl ayisyen","classification":"ht"},{"value":"*Dat enpòtan yo","name":"Haitian","natural":"Kreyòl ayisyen","classification":"ht"},{"value":"*Sa li fè, piblikasyon li nan domèn konesans matematik li","name":"Haitian","natural":"Kreyòl ayisyen","classification":"ht"},{"value":"*Referans pou konnen plis anlè moun sa a","name":"Haitian","natural":"Kreyòl ayisyen","classification":"ht"},{"value":" se yon matematisyen ameriken.","name":"Haitian","natural":"Kreyòl ayisyen","classification":"ht"},{"value":"*Dat enpòtan yo","name":"Haitian","natural":"Kreyòl ayisyen","classification":"ht"},{"value":"*Sa li fè, piblikasyon li nan domèn konesans matematik li","name":"Haitian","natural":"Kreyòl ayisyen","classification":"ht"},{"value":"*Referans pou konnen plis anlè moun sa a","name":"Haitian","natural":"Kreyòl ayisyen","classification":"ht"},{"value":" se yon komin nan pwovens Seville, nan kominote otonòm Andalouzi, nan peyi Espay. Li genyen (2002) 614 moun, nan lane 2005, li vini genyen 638 moun. Sipèfisi l se : 16,22 km^2.","name":"Haitian","natural":"Kreyòl ayisyen","classification":"ht"},{"value":"Istwa","name":"Haitian","natural":"Kreyòl ayisyen","classification":"ht"},{"value":" se yon vil Etazini. Li sitye nan leta Arkansas. Chèf-lye li se ? .","name":"Haitian","natural":"Kreyòl ayisyen","classification":"ht"},{"value":"Istwa","name":"Haitian","natural":"Kreyòl ayisyen","classification":"ht"},{"value":" se yon vil Etazini. Li sitye nan leta Florid. Chèf-lye li se ?","name":"Haitian","natural":"Kreyòl ayisyen","classification":"ht"},{"value":"Istwa","name":"Haitian","natural":"Kreyòl ayisyen","classification":"ht"},{"value":" se yon vil Etazini. Li sitye nan leta Florid. Chèf-lye li se ?","name":"Haitian","natural":"Kreyòl ayisyen","classification":"ht"},{"value":"Istwa","name":"Haitian","natural":"Kreyòl ayisyen","classification":"ht"},{"value":" se yon vil Etazini. Li sitye nan leta Georgie. Chèf-lye li se ?","name":"Haitian","natural":"Kreyòl ayisyen","classification":"ht"},{"value":"Istwa","name":"Haitian","natural":"Kreyòl ayisyen","classification":"ht"},{"value":" se yon vil Etazini. Li sitye nan leta Iowa. Chèf-lye li se ? .","name":"Haitian","natural":"Kreyòl ayisyen","classification":"ht"},{"value":"Istwa","name":"Haitian","natural":"Kreyòl ayisyen","classification":"ht"},{"value":" se yon gwoup rege, raga polonè","name":"Haitian","natural":"Kreyòl ayisyen","classification":"ht"},{"value":"*Dat enpòtan yo","name":"Haitian","natural":"Kreyòl ayisyen","classification":"ht"},{"value":"*Sa li fè","name":"Haitian","natural":"Kreyòl ayisyen","classification":"ht"},{"value":"*Referans pou konnen plis anlè moun sa a","name":"Haitian","natural":"Kreyòl ayisyen","classification":"ht"},{"value":" se yon vil Etazini. Li sitye nan leta Lwizyana. Chèf-lye li se ?.","name":"Haitian","natural":"Kreyòl ayisyen","classification":"ht"},{"value":"Istwa","name":"Haitian","natural":"Kreyòl ayisyen","classification":"ht"},{"value":" se yon vil Etazini. Li sitye nan leta Maine. Chèf-lye li se Washington.","name":"Haitian","natural":"Kreyòl ayisyen","classification":"ht"},{"value":"Istwa","name":"Haitian","natural":"Kreyòl ayisyen","classification":"ht"},{"value":"Bosworth  se yon vil nan eta  Missouri","name":"Haitian","natural":"Kreyòl ayisyen","classification":"ht"},{"value":"Istwa","name":"Haitian","natural":"Kreyòl ayisyen","classification":"ht"},{"value":"*Kominote Ayisyen, relasyon ant eta sa epi Ayiti","name":"Haitian","natural":"Kreyòl ayisyen","classification":"ht"},{"value":"Bakersfield  se yon vil nan eta  Missouri","name":"Haitian","natural":"Kreyòl ayisyen","classification":"ht"},{"value":"Istwa","name":"Haitian","natural":"Kreyòl ayisyen","classification":"ht"},{"value":"*Kominote Ayisyen, relasyon ant eta sa epi Ayiti","name":"Haitian","natural":"Kreyòl ayisyen","classification":"ht"},{"value":"Hartland  se yon vil nan eta  Nou yòk (New York) . Li nan konte, rejyon Niagara .","name":"Haitian","natural":"Kreyòl ayisyen","classification":"ht"},{"value":"Istwa","name":"Haitian","natural":"Kreyòl ayisyen","classification":"ht"},{"value":"*Kominote Ayisyen, relasyon ant eta sa epi Ayiti","name":"Haitian","natural":"Kreyòl ayisyen","classification":"ht"},{"value":"Granite Falls  se yon vil nan eta  Kawolin dinò, nan Etazini.","name":"Haitian","natural":"Kreyòl ayisyen","classification":"ht"},{"value":"Istwa","name":"Haitian","natural":"Kreyòl ayisyen","classification":"ht"},{"value":"*Kominote Ayisyen, relasyon ant eta sa epi Ayiti","name":"Haitian","natural":"Kreyòl ayisyen","classification":"ht"},{"value":"Barney  se yon vil nan eta  Dakota dinò, nan Etazini.","name":"Haitian","natural":"Kreyòl ayisyen","classification":"ht"},{"value":"Istwa","name":"Haitian","natural":"Kreyòl ayisyen","classification":"ht"},{"value":"*Kominote Ayisyen, relasyon ant eta sa epi Ayiti","name":"Haitian","natural":"Kreyòl ayisyen","classification":"ht"},{"value":"Fossil se yon vil nan eta Oregon, nan Etazini.","name":"Haitian","natural":"Kreyòl ayisyen","classification":"ht"},{"value":"Istwa","name":"Haitian","natural":"Kreyòl ayisyen","classification":"ht"},{"value":"*Kominote Ayisyen, relasyon ant eta sa epi Ayiti","name":"Haitian","natural":"Kreyòl ayisyen","classification":"ht"},{"value":"Wattsburg se yon vil nan eta Pennsilvani, nan Etazini.","name":"Haitian","natural":"Kreyòl ayisyen","classification":"ht"},{"value":"Istwa","name":"Haitian","natural":"Kreyòl ayisyen","classification":"ht"},{"value":"*Kominote Ayisyen, relasyon ant eta sa epi Ayiti","name":"Haitian","natural":"Kreyòl ayisyen","classification":"ht"},{"value":"Sullivan City se yon vil nan eta Texas, nan Etazini. Nan lane 2000 li te genyen 3,998 moun.","name":"Haitian","natural":"Kreyòl ayisyen","classification":"ht"},{"value":"Istwa","name":"Haitian","natural":"Kreyòl ayisyen","classification":"ht"},{"value":"*Kominote Ayisyen, relasyon ant eta sa epi Ayiti","name":"Haitian","natural":"Kreyòl ayisyen","classification":"ht"},{"value":"Cheney se yon vil nan eta Washington, nan Etazini.","name":"Haitian","natural":"Kreyòl ayisyen","classification":"ht"},{"value":"Istwa","name":"Haitian","natural":"Kreyòl ayisyen","classification":"ht"},{"value":"*Kominote Ayisyen, relasyon ant eta sa epi Ayiti","name":"Haitian","natural":"Kreyòl ayisyen","classification":"ht"},{"value":"Ceiba Hueca Arriba se yon vil nan pwovens Granma, nan peyi Kiba. Li genyen kèk 11938 moun.","name":"Haitian","natural":"Kreyòl ayisyen","classification":"ht"},{"value":"Istwa","name":"Haitian","natural":"Kreyòl ayisyen","classification":"ht"},{"value":"Ant Kiba e Ayiti genyen 90 km lanmè. Kreyòl ayisyen se dezyèm lang ki pale nan Kiba, lang ayisyen an gen menm yon estasyon radyo pou kò l.","name":"Haitian","natural":"Kreyòl ayisyen","classification":"ht"},{"value":"Gade : Tout gwo vil yo nan kat sa","name":"Haitian","natural":"Kreyòl ayisyen","classification":"ht"},{"value":"Moun sa yo se pèsonalite nan pwovens sa, men non yo rele :","name":"Haitian","natural":"Kreyòl ayisyen","classification":"ht"},{"value":"Los Cayos se yon vil nan pwovens Granma, nan peyi Kiba. Li genyen kèk 19129 moun.","name":"Haitian","natural":"Kreyòl ayisyen","classification":"ht"},{"value":"Istwa","name":"Haitian","natural":"Kreyòl ayisyen","classification":"ht"},{"value":"Ant Kiba e Ayiti genyen 90 km lanmè. Kreyòl ayisyen se dezyèm lang ki pale nan Kiba, lang ayisyen an gen menm yon estasyon radyo pou kò l.","name":"Haitian","natural":"Kreyòl ayisyen","classification":"ht"},{"value":"Gade : Tout gwo vil yo nan kat sa","name":"Haitian","natural":"Kreyòl ayisyen","classification":"ht"},{"value":"Moun sa yo se pèsonalite nan pwovens sa, men non yo rele :","name":"Haitian","natural":"Kreyòl ayisyen","classification":"ht"},{"value":"La Calera se yon vil nan pwovens Matanzas, nan peyi Kiba. Li genyen kèk 13507 moun. Detay jewografik :","name":"Haitian","natural":"Kreyòl ayisyen","classification":"ht"},{"value":"Istwa","name":"Haitian","natural":"Kreyòl ayisyen","classification":"ht"},{"value":"Kreyòl ayisyen se dezyèm lang ki pale nan Kiba, lang ayisyen an gen menm yon estasyon radyo pou kò l.","name":"Haitian","natural":"Kreyòl ayisyen","classification":"ht"},{"value":"* FallInGrain, vil ak estatistik Gade : Tout gwo vil yo nan pwovens sa nan kat sa","name":"Haitian","natural":"Kreyòl ayisyen","classification":"ht"},{"value":"Moun sa yo se pèsonalite nan pwovens sa, men non yo rele :","name":"Haitian","natural":"Kreyòl ayisyen","classification":"ht"},{"value":"Estratifikasyon se yon eschistozite orizontal nan wòch sedimantè ki ka deplwaye sou yon milimèt nan epesè a plizyè mèt nan epesè.","name":"Haitian","natural":"Kreyòl ayisyen","classification":"ht"},{"value":"Ansyen popiulasyon Perwou pwononcé Pewou n'an son leingue ahytian ha khi seid kreyòl","name":"Haitian","natural":"Kreyòl ayisyen","classification":"ht"},{"value":"1345 se 1390 m ane nan almanak jilyen. Gade osi nonm 1345.","name":"Haitian","natural":"Kreyòl ayisyen","classification":"ht"},{"value":"Se yon rejyon nan peyi Frans.","name":"Haitian","natural":"Kreyòl ayisyen","classification":"ht"},{"value":" se yon ekriven. Li ekri liv konsène Ayiti oubyen kreyòl ayisyen oubyen nan karayib an.","name":"Haitian","natural":"Kreyòl ayisyen","classification":"ht"},{"value":"*Dat enpòtan yo","name":"Haitian","natural":"Kreyòl ayisyen","classification":"ht"},{"value":"*Sa li fè","name":"Haitian","natural":"Kreyòl ayisyen","classification":"ht"},{"value":"*Referans pou konnen plis anlè moun sa a","name":"Haitian","natural":"Kreyòl ayisyen","classification":"ht"},{"value":"Moise Kharmeliaud gen pou vre prenon Camille, men li chwazi siyen tout fim li yo sou prenon Kharmeliaud ki se prenon pitit gason l. Li se yon aktè ak reyalizatè ayisyen.","name":"Haitian","natural":"Kreyòl ayisyen","classification":"ht"},{"value":"Moise fet bò kote de fer 2 me 1978. Apre etid klasik li, li etidye kominikasyon sosyal avèk metye jounalis; men depi 1995 li koumanse nan reyalizasyon ki vinn tounen sèl pwofesyon li ekzèse. Moise travay anpil nan mond odyovizyèl ayisyen an. Li pase plis pase 3 lane ap kolabore avèk Mancuso pwodiksyon nan zafè piblisite emisyon televizyon ak dokimantè kote li te okipe plizyè fonksyon tankou kameramann, montè, reyalizatè, responsab pwodiksyon. Nan lane 2003, Moise Kharmeliaud fè wout pa li ann endepandan; depi lè sa, lap travay nan sinema kote li pwodwi epi reyalize plizyè fim ki fè diferans sou plan teknik. Apre yon fomasyon sou sinema dokimantè li resvwa nan FEMIS, nan Frans, Kharmeliaud vin konsantre plis sou fim dokimantè kote li kolabore ak kèk lot reyalizatè tankou Arnold Antonin, Renaud Dumenil.","name":"Haitian","natural":"Kreyòl ayisyen","classification":"ht"},{"value":"Schudson Boursiquot se yon aktè ayisyen.","name":"Haitian","natural":"Kreyòl ayisyen","classification":"ht"},{"value":"*Dat enpòtan yo","name":"Haitian","natural":"Kreyòl ayisyen","classification":"ht"},{"value":"* Schudson Boursiquot IMDB","name":"Haitian","natural":"Kreyòl ayisyen","classification":"ht"},{"value":"Gilbert Desir se yon atis, yon pent ayisyen.","name":"Haitian","natural":"Kreyòl ayisyen","classification":"ht"},{"value":"*Dat enpòtan yo","name":"Haitian","natural":"Kreyòl ayisyen","classification":"ht"},{"value":"*Sa li fè","name":"Haitian","natural":"Kreyòl ayisyen","classification":"ht"},{"value":"*[http://www.webster.edu/~corbetre/haiti/art/artist-list.html Yon lis atis pent ayisyen ak byografi] *kèk lyen ...","name":"Haitian","natural":"Kreyòl ayisyen","classification":"ht"},{"value":"Anil Nerode se yon matematisyen ameriken.","name":"Haitian","natural":"Kreyòl ayisyen","classification":"ht"},{"value":"*Dat enpòtan yo","name":"Haitian","natural":"Kreyòl ayisyen","classification":"ht"},{"value":"*Sa li fè, piblikasyon li nan domèn konesans matematik li","name":"Haitian","natural":"Kreyòl ayisyen","classification":"ht"},{"value":"*Referans pou konnen plis anlè moun sa a","name":"Haitian","natural":"Kreyòl ayisyen","classification":"ht"},{"value":"George Thomas se yon matematisyen ameriken.","name":"Haitian","natural":"Kreyòl ayisyen","classification":"ht"},{"value":"*Dat enpòtan yo","name":"Haitian","natural":"Kreyòl ayisyen","classification":"ht"},{"value":"*Sa li fè, piblikasyon li nan domèn konesans matematik li","name":"Haitian","natural":"Kreyòl ayisyen","classification":"ht"},{"value":"*Referans pou konnen plis anlè moun sa a","name":"Haitian","natural":"Kreyòl ayisyen","classification":"ht"},{"value":"Bernard Morin se yon matematisyen franse. Li se yon moun avèg.","name":"Haitian","natural":"Kreyòl ayisyen","classification":"ht"},{"value":"*Dat enpòtan yo","name":"Haitian","natural":"Kreyòl ayisyen","classification":"ht"},{"value":"*Sa li fè, piblikasyon li nan domèn konesans matematik li","name":"Haitian","natural":"Kreyòl ayisyen","classification":"ht"},{"value":"*Referans pou konnen plis anlè moun sa a","name":"Haitian","natural":"Kreyòl ayisyen","classification":"ht"},{"value":" se yon matematisyen ris, nan peyi Risi.","name":"Haitian","natural":"Kreyòl ayisyen","classification":"ht"},{"value":"*Dat enpòtan yo","name":"Haitian","natural":"Kreyòl ayisyen","classification":"ht"},{"value":"*Sa li fè, piblikasyon li nan domèn konesans matematik li","name":"Haitian","natural":"Kreyòl ayisyen","classification":"ht"},{"value":"*Referans pou konnen plis anlè moun sa a","name":"Haitian","natural":"Kreyòl ayisyen","classification":"ht"},{"value":" se yon komin nan pwovens Cadix, nan kominote otonòm Andalouzi, nan peyi Espay. Li genyen (2002) 136.236 moun. Sipèfisi l se 131.813 Km^2","name":"Haitian","natural":"Kreyòl ayisyen","classification":"ht"},{"value":"Istwa","name":"Haitian","natural":"Kreyòl ayisyen","classification":"ht"},{"value":" se yon komin nan pwovens Huelva, nan kominote otonòm Andalouzi, nan peyi Espay.","name":"Haitian","natural":"Kreyòl ayisyen","classification":"ht"},{"value":"Istwa","name":"Haitian","natural":"Kreyòl ayisyen","classification":"ht"},{"value":" se yon foutbalè ayisyen. Li jwe nan ekip sa : *ki ekip ?","name":"Haitian","natural":"Kreyòl ayisyen","classification":"ht"},{"value":"*Dat enpòtan yo","name":"Haitian","natural":"Kreyòl ayisyen","classification":"ht"},{"value":"*Sa li fè","name":"Haitian","natural":"Kreyòl ayisyen","classification":"ht"},{"value":"*Referans pou konnen plis anlè moun sa a","name":"Haitian","natural":"Kreyòl ayisyen","classification":"ht"},{"value":" se yon vil Etazini. Li sitye nan leta Alabama. Chèf-lye li se Tuscaloosa .","name":"Haitian","natural":"Kreyòl ayisyen","classification":"ht"},{"value":"Istwa","name":"Haitian","natural":"Kreyòl ayisyen","classification":"ht"},{"value":" se yon vil Etazini. Li sitye nan leta Kolorado. Chèf-lye li se ? .","name":"Haitian","natural":"Kreyòl ayisyen","classification":"ht"},{"value":"Istwa","name":"Haitian","natural":"Kreyòl ayisyen","classification":"ht"},{"value":" se yon vil Etazini. Li sitye nan leta Iowa. Chèf-lye li se ? .","name":"Haitian","natural":"Kreyòl ayisyen","classification":"ht"},{"value":"Istwa","name":"Haitian","natural":"Kreyòl ayisyen","classification":"ht"},{"value":" se yon gwoup rege, raga angle","name":"Haitian","natural":"Kreyòl ayisyen","classification":"ht"},{"value":"*Dat enpòtan yo","name":"Haitian","natural":"Kreyòl ayisyen","classification":"ht"},{"value":"*Sa li fè","name":"Haitian","natural":"Kreyòl ayisyen","classification":"ht"},{"value":"*Referans pou konnen plis anlè moun sa a","name":"Haitian","natural":"Kreyòl ayisyen","classification":"ht"},{"value":" se yon vil Etazini. Li sitye nan leta Indiana. Chèf-lye li se ? Nan lane 2004, popilasyon l te konte 236 moun. Lòt lane yo te genyen : 2003 (233),","name":"Haitian","natural":"Kreyòl ayisyen","classification":"ht"},{"value":"Istwa","name":"Haitian","natural":"Kreyòl ayisyen","classification":"ht"},{"value":" se yon vil Etazini. Li sitye nan leta Kentucky. Chèf-lye li se ?.","name":"Haitian","natural":"Kreyòl ayisyen","classification":"ht"},{"value":"Istwa","name":"Haitian","natural":"Kreyòl ayisyen","classification":"ht"},{"value":"Se yon pwofesè nan inivèsite Florid. L ap travay sou teknoloji pwopilsyon pa Manyeto-Idwodinamik (MHD). Li mande yon brevè pou yon machin li konstwi ak teknoloji sa, li rele l : WEAV (pou veyikil nan syèl elektwomanyetik san zèl )","name":"Haitian","natural":"Kreyòl ayisyen","classification":"ht"},{"value":"René Chalmers  te yon minis zafè diplomatik ayisyen pandan laprezidans François Duvalier. Manda li te an 1961 - 1971.","name":"Haitian","natural":"Kreyòl ayisyen","classification":"ht"},{"value":"*Dat enpòtan yo","name":"Haitian","natural":"Kreyòl ayisyen","classification":"ht"},{"value":"*Sa li fè","name":"Haitian","natural":"Kreyòl ayisyen","classification":"ht"},{"value":"*Referans pou konnen plis anlè moun sa a","name":"Haitian","natural":"Kreyòl ayisyen","classification":"ht"},{"value":"Catron  se yon vil nan eta  Missouri","name":"Haitian","natural":"Kreyòl ayisyen","classification":"ht"},{"value":"Istwa","name":"Haitian","natural":"Kreyòl ayisyen","classification":"ht"},{"value":"*Kominote Ayisyen, relasyon ant eta sa epi Ayiti","name":"Haitian","natural":"Kreyòl ayisyen","classification":"ht"},{"value":"Wilsonville  se yon vil nan eta  Nebraska .","name":"Haitian","natural":"Kreyòl ayisyen","classification":"ht"},{"value":"Istwa","name":"Haitian","natural":"Kreyòl ayisyen","classification":"ht"},{"value":"*Kominote Ayisyen, relasyon ant eta sa epi Ayiti","name":"Haitian","natural":"Kreyòl ayisyen","classification":"ht"},{"value":"Alton se yon vil nan eta New Hampshire .","name":"Haitian","natural":"Kreyòl ayisyen","classification":"ht"},{"value":"Istwa","name":"Haitian","natural":"Kreyòl ayisyen","classification":"ht"},{"value":"* Kominote Ayisyen, relasyon ant eta sa epi Ayiti","name":"Haitian","natural":"Kreyòl ayisyen","classification":"ht"},{"value":"Union Springs  se yon vil nan eta  Nou yòk (New York) . Li nan konte, rejyon Cayuga .","name":"Haitian","natural":"Kreyòl ayisyen","classification":"ht"},{"value":"Istwa","name":"Haitian","natural":"Kreyòl ayisyen","classification":"ht"},{"value":"*Kominote Ayisyen, relasyon ant eta sa epi Ayiti","name":"Haitian","natural":"Kreyòl ayisyen","classification":"ht"},{"value":"Arkoma se yon vil nan eta Oklahoma, nan Etazini.","name":"Haitian","natural":"Kreyòl ayisyen","classification":"ht"},{"value":"Istwa","name":"Haitian","natural":"Kreyòl ayisyen","classification":"ht"},{"value":"*Kominote Ayisyen, relasyon ant eta sa epi Ayiti","name":"Haitian","natural":"Kreyòl ayisyen","classification":"ht"},{"value":"Long Lake se yon vil nan eta Dakota disid, nan Etazini.","name":"Haitian","natural":"Kreyòl ayisyen","classification":"ht"},{"value":"Istwa","name":"Haitian","natural":"Kreyòl ayisyen","classification":"ht"},{"value":"*Kominote Ayisyen, relasyon ant eta sa epi Ayiti","name":"Haitian","natural":"Kreyòl ayisyen","classification":"ht"},{"value":"Tellico Plains se yon vil nan eta Tennessee, nan Etazini. Li nan konte, rejyon Monroe. Nan lane 2000, popilasyon l te genyen 859 moun.","name":"Haitian","natural":"Kreyòl ayisyen","classification":"ht"},{"value":"Istwa","name":"Haitian","natural":"Kreyòl ayisyen","classification":"ht"},{"value":"*Kominote Ayisyen, relasyon ant eta sa epi Ayiti","name":"Haitian","natural":"Kreyòl ayisyen","classification":"ht"},{"value":"Bunker Hill Village se yon vil nan eta Texas, nan Etazini. Nan lane 2000 li te genyen 3,654 moun.","name":"Haitian","natural":"Kreyòl ayisyen","classification":"ht"},{"value":"Istwa","name":"Haitian","natural":"Kreyòl ayisyen","classification":"ht"},{"value":"*Kominote Ayisyen, relasyon ant eta sa epi Ayiti","name":"Haitian","natural":"Kreyòl ayisyen","classification":"ht"},{"value":"Matador se yon vil nan eta Texas, nan Etazini. Nan lane 2000 li te genyen 740 moun.","name":"Haitian","natural":"Kreyòl ayisyen","classification":"ht"},{"value":"Istwa","name":"Haitian","natural":"Kreyòl ayisyen","classification":"ht"},{"value":"*Kominote Ayisyen, relasyon ant eta sa epi Ayiti","name":"Haitian","natural":"Kreyòl ayisyen","classification":"ht"},{"value":"La Feria North se yon vil nan eta Texas, nan Etazini. Nan lane 2000 li te genyen 168 moun.","name":"Haitian","natural":"Kreyòl ayisyen","classification":"ht"},{"value":"Istwa","name":"Haitian","natural":"Kreyòl ayisyen","classification":"ht"},{"value":"*Kominote Ayisyen, relasyon ant eta sa epi Ayiti","name":"Haitian","natural":"Kreyòl ayisyen","classification":"ht"},{"value":"Scipio se yon vil nan eta Utah, nan Etazini.","name":"Haitian","natural":"Kreyòl ayisyen","classification":"ht"},{"value":"Istwa","name":"Haitian","natural":"Kreyòl ayisyen","classification":"ht"},{"value":"*Kominote Ayisyen, relasyon ant eta sa epi Ayiti","name":"Haitian","natural":"Kreyòl ayisyen","classification":"ht"},{"value":"Thayne se yon vil nan eta Wyoming, nan Etazini. Li nan konte, rejyon Lincoln . Nan lane 2000, popilasyon li te genyen 341 moun.","name":"Haitian","natural":"Kreyòl ayisyen","classification":"ht"},{"value":"Istwa","name":"Haitian","natural":"Kreyòl ayisyen","classification":"ht"},{"value":"* Kominote Ayisyen, relasyon ant eta sa epi Ayiti","name":"Haitian","natural":"Kreyòl ayisyen","classification":"ht"},{"value":"Mandinga se yon vil nan pwovens Cienfuegos, nan peyi Kiba. Li genyen kèk 11647 moun. Detay jewografik :","name":"Haitian","natural":"Kreyòl ayisyen","classification":"ht"},{"value":"Istwa","name":"Haitian","natural":"Kreyòl ayisyen","classification":"ht"},{"value":"Ant Kiba e Ayiti genyen 90 km lanmè. Kreyòl ayisyen se dezyèm lang ki pale nan Kiba, lang ayisyen an gen menm yon estasyon radyo pou kò l.","name":"Haitian","natural":"Kreyòl ayisyen","classification":"ht"},{"value":"Gade : Tout gwo vil yo nan kat sa","name":"Haitian","natural":"Kreyòl ayisyen","classification":"ht"},{"value":"Moun sa yo se pèsonalite nan pwovens sa, men non yo rele :","name":"Haitian","natural":"Kreyòl ayisyen","classification":"ht"},{"value":"Itabo se yon vil nan pwovens Sancti Spiritus, nan peyi Kiba. Li genyen kèk 5833 moun.","name":"Haitian","natural":"Kreyòl ayisyen","classification":"ht"},{"value":"Istwa","name":"Haitian","natural":"Kreyòl ayisyen","classification":"ht"},{"value":"Ant Kiba e Ayiti genyen 90 km lanmè. Kreyòl ayisyen se dezyèm lang ki pale nan Kiba, lang ayisyen an gen menm yon estasyon radyo pou kò l.","name":"Haitian","natural":"Kreyòl ayisyen","classification":"ht"},{"value":"Gade : Tout gwo vil yo nan kat sa","name":"Haitian","natural":"Kreyòl ayisyen","classification":"ht"},{"value":"Moun sa yo se pèsonalite nan pwovens sa, men non yo rele :","name":"Haitian","natural":"Kreyòl ayisyen","classification":"ht"},{"value":"Sucesores de Catalina Gallo se yon vil nan pwovens Sancti Spiritus, nan peyi Kiba. Li genyen kèk 6787 moun.","name":"Haitian","natural":"Kreyòl ayisyen","classification":"ht"},{"value":"Istwa","name":"Haitian","natural":"Kreyòl ayisyen","classification":"ht"},{"value":"Ant Kiba e Ayiti genyen 90 km lanmè. Kreyòl ayisyen se dezyèm lang ki pale nan Kiba, lang ayisyen an gen menm yon estasyon radyo pou kò l.","name":"Haitian","natural":"Kreyòl ayisyen","classification":"ht"},{"value":"Gade : Tout gwo vil yo nan kat sa","name":"Haitian","natural":"Kreyòl ayisyen","classification":"ht"},{"value":"Moun sa yo se pèsonalite nan pwovens sa, men non yo rele :","name":"Haitian","natural":"Kreyòl ayisyen","classification":"ht"},{"value":"La Manila se yon vil nan pwovens Pinar del Rio, nan peyi Kiba. Li genyen kèk 10446 moun. Detay jewografik :","name":"Haitian","natural":"Kreyòl ayisyen","classification":"ht"},{"value":"Istwa","name":"Haitian","natural":"Kreyòl ayisyen","classification":"ht"},{"value":"Kreyòl ayisyen se dezyèm lang ki pale nan Kiba, lang ayisyen an gen menm yon estasyon radyo pou kò l.","name":"Haitian","natural":"Kreyòl ayisyen","classification":"ht"},{"value":"* FallInGrain, vil ak estatistik Gade : Tout gwo vil yo nan pwovens sa nan kat sa","name":"Haitian","natural":"Kreyòl ayisyen","classification":"ht"},{"value":"Moun sa yo se pèsonalite nan pwovens sa, men non yo rele :","name":"Haitian","natural":"Kreyòl ayisyen","classification":"ht"},{"value":"Nodarse se yon vil nan pwovens Pinar del Rio, nan peyi Kiba. Li genyen kèk 10517 moun. Detay jewografik :","name":"Haitian","natural":"Kreyòl ayisyen","classification":"ht"},{"value":"Istwa","name":"Haitian","natural":"Kreyòl ayisyen","classification":"ht"},{"value":"Kreyòl ayisyen se dezyèm lang ki pale nan Kiba, lang ayisyen an gen menm yon estasyon radyo pou kò l.","name":"Haitian","natural":"Kreyòl ayisyen","classification":"ht"},{"value":"* FallInGrain, vil ak estatistik Gade : Tout gwo vil yo nan pwovens sa nan kat sa","name":"Haitian","natural":"Kreyòl ayisyen","classification":"ht"},{"value":"Moun sa yo se pèsonalite nan pwovens sa, men non yo rele :","name":"Haitian","natural":"Kreyòl ayisyen","classification":"ht"},{"value":"La America se yon vil nan pwovens Matanzas, nan peyi Kiba. Li genyen kèk 10410 moun. Detay jewografik :","name":"Haitian","natural":"Kreyòl ayisyen","classification":"ht"},{"value":"Istwa","name":"Haitian","natural":"Kreyòl ayisyen","classification":"ht"},{"value":"Kreyòl ayisyen se dezyèm lang ki pale nan Kiba, lang ayisyen an gen menm yon estasyon radyo pou kò l.","name":"Haitian","natural":"Kreyòl ayisyen","classification":"ht"},{"value":"* FallInGrain, vil ak estatistik Gade : Tout gwo vil yo nan pwovens sa nan kat sa","name":"Haitian","natural":"Kreyòl ayisyen","classification":"ht"},{"value":"Moun sa yo se pèsonalite nan pwovens sa, men non yo rele :","name":"Haitian","natural":"Kreyòl ayisyen","classification":"ht"},{"value":"30 jiyè se 211 m jou lane (oubyen 212 m nan lane bisektil) nan almanak gregoryen.","name":"Haitian","natural":"Kreyòl ayisyen","classification":"ht"},{"value":"Oklawoma se yon eta Ozetazini.","name":"Haitian","natural":"Kreyòl ayisyen","classification":"ht"},{"value":"ק se glif ki reprezante yon lèt nan alfabèt ebre. Ann ebre mòdèn, li pwononse toujou tankou \"k\".","name":"Haitian","natural":"Kreyòl ayisyen","classification":"ht"},{"value":"637 se yon nonm. Pou ekri li, yo itilize chif arab yo.","name":"Haitian","natural":"Kreyòl ayisyen","classification":"ht"},{"value":"Se nonm antye natirèl ant 636 ak 638 nan sistèm desimal.","name":"Haitian","natural":"Kreyòl ayisyen","classification":"ht"},{"value":"140 se yon nonm. Pou ekri li, yo itilize chif arab yo.","name":"Haitian","natural":"Kreyòl ayisyen","classification":"ht"},{"value":"Se nonm antye natirèl ant 139 ak 141 nan sistèm desimal.","name":"Haitian","natural":"Kreyòl ayisyen","classification":"ht"},{"value":"90 se 135 m ane nan almanak jilyen. Gade osi nonm 90.","name":"Haitian","natural":"Kreyòl ayisyen","classification":"ht"},{"value":" se yon Ayisyen . Li se yon atis, mizisyen kreyòl. Li ap jwe mizik sa : ? Li ap jwe nan gwoup sa : ?","name":"Haitian","natural":"Kreyòl ayisyen","classification":"ht"},{"value":"*Dat enpòtan yo","name":"Haitian","natural":"Kreyòl ayisyen","classification":"ht"},{"value":"*Sa li fè","name":"Haitian","natural":"Kreyòl ayisyen","classification":"ht"},{"value":"*Referans pou konnen plis anlè moun sa a","name":"Haitian","natural":"Kreyòl ayisyen","classification":"ht"},{"value":" se yon matematisyen franse.","name":"Haitian","natural":"Kreyòl ayisyen","classification":"ht"},{"value":"*Dat enpòtan yo","name":"Haitian","natural":"Kreyòl ayisyen","classification":"ht"},{"value":"*Sa li fè, piblikasyon li nan domèn konesans matematik li","name":"Haitian","natural":"Kreyòl ayisyen","classification":"ht"},{"value":"*Referans pou konnen plis anlè moun sa a","name":"Haitian","natural":"Kreyòl ayisyen","classification":"ht"},{"value":" se yon vil Etazini. Li sitye nan leta Kolorado. Chèf-lye li se ? .","name":"Haitian","natural":"Kreyòl ayisyen","classification":"ht"},{"value":"Istwa","name":"Haitian","natural":"Kreyòl ayisyen","classification":"ht"},{"value":" se yon vil Etazini. Li sitye nan leta Georgie. Chèf-lye li se ?","name":"Haitian","natural":"Kreyòl ayisyen","classification":"ht"},{"value":"Istwa","name":"Haitian","natural":"Kreyòl ayisyen","classification":"ht"},{"value":" se yon vil Etazini. Li sitye nan leta Kentucky. Chèf-lye li se ?.","name":"Haitian","natural":"Kreyòl ayisyen","classification":"ht"},{"value":"Istwa","name":"Haitian","natural":"Kreyòl ayisyen","classification":"ht"},{"value":" se yon vil Etazini. Li sitye nan leta Lwizyana. Chèf-lye li se ?.","name":"Haitian","natural":"Kreyòl ayisyen","classification":"ht"},{"value":"Istwa","name":"Haitian","natural":"Kreyòl ayisyen","classification":"ht"},{"value":" se yon vil Etazini. Li sitye nan leta Maine. Chèf-lye li se Piscataquis.","name":"Haitian","natural":"Kreyòl ayisyen","classification":"ht"},{"value":"Istwa","name":"Haitian","natural":"Kreyòl ayisyen","classification":"ht"},{"value":"Hutchinson  se yon vil nan eta  Minnesota, nan Etazini.","name":"Haitian","natural":"Kreyòl ayisyen","classification":"ht"},{"value":"Istwa","name":"Haitian","natural":"Kreyòl ayisyen","classification":"ht"},{"value":"*Kominote Ayisyen, relasyon ant eta sa epi Ayiti","name":"Haitian","natural":"Kreyòl ayisyen","classification":"ht"},{"value":"Sturgis  se yon vil nan eta  Mississippi .","name":"Haitian","natural":"Kreyòl ayisyen","classification":"ht"},{"value":"Istwa","name":"Haitian","natural":"Kreyòl ayisyen","classification":"ht"},{"value":"*Kominote Ayisyen, relasyon ant eta sa epi Ayiti","name":"Haitian","natural":"Kreyòl ayisyen","classification":"ht"},{"value":"Saint Paul  se yon vil nan eta  Nebraska .","name":"Haitian","natural":"Kreyòl ayisyen","classification":"ht"},{"value":"Istwa","name":"Haitian","natural":"Kreyòl ayisyen","classification":"ht"},{"value":"*Kominote Ayisyen, relasyon ant eta sa epi Ayiti","name":"Haitian","natural":"Kreyòl ayisyen","classification":"ht"},{"value":"Upper Pittsgrove  se yon vil nan eta  New Jersey . Li nan konte Salem Li te genyen nan lane 2000 3468   moun.","name":"Haitian","natural":"Kreyòl ayisyen","classification":"ht"},{"value":"Istwa","name":"Haitian","natural":"Kreyòl ayisyen","classification":"ht"},{"value":"*Kominote Ayisyen, relasyon ant eta sa epi Ayiti","name":"Haitian","natural":"Kreyòl ayisyen","classification":"ht"},{"value":"Hewlett Neck se yon vil nan eta Nou yòk (New York) . Li nan konte, rejyon Nassau .","name":"Haitian","natural":"Kreyòl ayisyen","classification":"ht"},{"value":"Istwa","name":"Haitian","natural":"Kreyòl ayisyen","classification":"ht"},{"value":"* Kominote Ayisyen, relasyon ant eta sa epi Ayiti","name":"Haitian","natural":"Kreyòl ayisyen","classification":"ht"},{"value":"Coshocton  se yon vil nan eta  Ohio, nan Etazini. Popilasyon l nan lane 2000 te genyen 11,682  moun. Li nan konte, rejyon Coshocton  .","name":"Haitian","natural":"Kreyòl ayisyen","classification":"ht"},{"value":"Istwa","name":"Haitian","natural":"Kreyòl ayisyen","classification":"ht"},{"value":"*Kominote Ayisyen, relasyon ant eta sa epi Ayiti","name":"Haitian","natural":"Kreyòl ayisyen","classification":"ht"},{"value":"Lakemore  se yon vil nan eta  Ohio, nan Etazini. Popilasyon l nan lane 2000 te genyen 2,561   moun. Li nan konte, rejyon   Summit .","name":"Haitian","natural":"Kreyòl ayisyen","classification":"ht"},{"value":"Istwa","name":"Haitian","natural":"Kreyòl ayisyen","classification":"ht"},{"value":"*Kominote Ayisyen, relasyon ant eta sa epi Ayiti","name":"Haitian","natural":"Kreyòl ayisyen","classification":"ht"},{"value":"Windham  se yon vil nan eta  Ohio, nan Etazini. Popilasyon l nan lane 2000 te genyen 2,806   moun. Li nan konte, rejyon   Portage .","name":"Haitian","natural":"Kreyòl ayisyen","classification":"ht"},{"value":"Istwa","name":"Haitian","natural":"Kreyòl ayisyen","classification":"ht"},{"value":"*Kominote Ayisyen, relasyon ant eta sa epi Ayiti","name":"Haitian","natural":"Kreyòl ayisyen","classification":"ht"},{"value":"Bridge se yon vil nan eta Oregon, nan Etazini.","name":"Haitian","natural":"Kreyòl ayisyen","classification":"ht"},{"value":"Istwa","name":"Haitian","natural":"Kreyòl ayisyen","classification":"ht"},{"value":"*Kominote Ayisyen, relasyon ant eta sa epi Ayiti","name":"Haitian","natural":"Kreyòl ayisyen","classification":"ht"},{"value":"Friendsville se yon vil nan eta Pennsilvani, nan Etazini.","name":"Haitian","natural":"Kreyòl ayisyen","classification":"ht"},{"value":"Istwa","name":"Haitian","natural":"Kreyòl ayisyen","classification":"ht"},{"value":"*Kominote Ayisyen, relasyon ant eta sa epi Ayiti","name":"Haitian","natural":"Kreyòl ayisyen","classification":"ht"},{"value":"North Catasauqua se yon vil nan eta Pennsilvani, nan Etazini.","name":"Haitian","natural":"Kreyòl ayisyen","classification":"ht"},{"value":"Istwa","name":"Haitian","natural":"Kreyòl ayisyen","classification":"ht"},{"value":"*Kominote Ayisyen, relasyon ant eta sa epi Ayiti","name":"Haitian","natural":"Kreyòl ayisyen","classification":"ht"},{"value":"Salladasburg se yon vil nan eta Pennsilvani, nan Etazini.","name":"Haitian","natural":"Kreyòl ayisyen","classification":"ht"},{"value":"Istwa","name":"Haitian","natural":"Kreyòl ayisyen","classification":"ht"},{"value":"*Kominote Ayisyen, relasyon ant eta sa epi Ayiti","name":"Haitian","natural":"Kreyòl ayisyen","classification":"ht"},{"value":"Utica se yon vil nan eta Dakota disid, nan Etazini.","name":"Haitian","natural":"Kreyòl ayisyen","classification":"ht"},{"value":"Istwa","name":"Haitian","natural":"Kreyòl ayisyen","classification":"ht"},{"value":"* Kominote Ayisyen, relasyon ant eta sa epi Ayiti","name":"Haitian","natural":"Kreyòl ayisyen","classification":"ht"},{"value":"Lago se yon vil nan eta Texas, nan Etazini. Nan lane 2000 li te genyen 246 moun.","name":"Haitian","natural":"Kreyòl ayisyen","classification":"ht"},{"value":"Istwa","name":"Haitian","natural":"Kreyòl ayisyen","classification":"ht"},{"value":"*Kominote Ayisyen, relasyon ant eta sa epi Ayiti","name":"Haitian","natural":"Kreyòl ayisyen","classification":"ht"},{"value":"Woodmohr se yon vil nan eta Wisconsin, nan Etazini. Li nan konte, rejyon Chippewa.","name":"Haitian","natural":"Kreyòl ayisyen","classification":"ht"},{"value":"Istwa","name":"Haitian","natural":"Kreyòl ayisyen","classification":"ht"},{"value":"*Kominote Ayisyen, relasyon ant eta sa epi Ayiti","name":"Haitian","natural":"Kreyòl ayisyen","classification":"ht"},{"value":"Zona de Calicito se yon vil nan pwovens Granma, nan peyi Kiba. Li genyen kèk 27396 moun.","name":"Haitian","natural":"Kreyòl ayisyen","classification":"ht"},{"value":"Istwa","name":"Haitian","natural":"Kreyòl ayisyen","classification":"ht"},{"value":"Ant Kiba e Ayiti genyen 90 km lanmè. Kreyòl ayisyen se dezyèm lang ki pale nan Kiba, lang ayisyen an gen menm yon estasyon radyo pou kò l.","name":"Haitian","natural":"Kreyòl ayisyen","classification":"ht"},{"value":"Gade : Tout gwo vil yo nan kat sa","name":"Haitian","natural":"Kreyòl ayisyen","classification":"ht"},{"value":"Moun sa yo se pèsonalite nan pwovens sa, men non yo rele :","name":"Haitian","natural":"Kreyòl ayisyen","classification":"ht"},{"value":"Azanza se yon vil nan pwovens Las Tunas, nan peyi Kiba. Li genyen kèk 7455 moun.","name":"Haitian","natural":"Kreyòl ayisyen","classification":"ht"},{"value":"Istwa","name":"Haitian","natural":"Kreyòl ayisyen","classification":"ht"},{"value":"Ant Kiba e Ayiti genyen 90 km lanmè. Kreyòl ayisyen se dezyèm lang ki pale nan Kiba, lang ayisyen an gen menm yon estasyon radyo pou kò l.","name":"Haitian","natural":"Kreyòl ayisyen","classification":"ht"},{"value":"Gade : Tout gwo vil yo nan kat sa","name":"Haitian","natural":"Kreyòl ayisyen","classification":"ht"},{"value":"Moun sa yo se pèsonalite nan pwovens sa, men non yo rele :","name":"Haitian","natural":"Kreyòl ayisyen","classification":"ht"},{"value":"El Alambre se yon vil nan pwovens Santiago de Cuba, nan peyi Kiba. Li genyen kèk 19302 moun.","name":"Haitian","natural":"Kreyòl ayisyen","classification":"ht"},{"value":"Istwa","name":"Haitian","natural":"Kreyòl ayisyen","classification":"ht"},{"value":"Ant Kiba e Ayiti genyen 90 km lanmè. Kreyòl ayisyen se dezyèm lang ki pale nan Kiba, lang ayisyen an gen menm yon estasyon radyo pou kò l.","name":"Haitian","natural":"Kreyòl ayisyen","classification":"ht"},{"value":"Gade : Tout gwo vil yo nan kat sa","name":"Haitian","natural":"Kreyòl ayisyen","classification":"ht"},{"value":"Moun sa yo se pèsonalite nan pwovens sa, men non yo rele :","name":"Haitian","natural":"Kreyòl ayisyen","classification":"ht"},{"value":"Luis Torres se yon vil nan pwovens Matanzas, nan peyi Kiba. Li genyen kèk 12607 moun. Detay jewografik :","name":"Haitian","natural":"Kreyòl ayisyen","classification":"ht"},{"value":"Istwa","name":"Haitian","natural":"Kreyòl ayisyen","classification":"ht"},{"value":"Kreyòl ayisyen se dezyèm lang ki pale nan Kiba, lang ayisyen an gen menm yon estasyon radyo pou kò l.","name":"Haitian","natural":"Kreyòl ayisyen","classification":"ht"},{"value":"* FallInGrain, vil ak estatistik Gade : Tout gwo vil yo nan pwovens sa nan kat sa","name":"Haitian","natural":"Kreyòl ayisyen","classification":"ht"},{"value":"Moun sa yo se pèsonalite nan pwovens sa, men non yo rele :","name":"Haitian","natural":"Kreyòl ayisyen","classification":"ht"},{"value":"== Zèv li yo ==","name":"Haitian","natural":"Kreyòl ayisyen","classification":"ht"},{"value":"* 1975 : Pantaleón y las visitadoras : \"La Brasileña\"","name":"Haitian","natural":"Kreyòl ayisyen","classification":"ht"},{"value":"<references />","name":"Haitian","natural":"Kreyòl ayisyen","classification":"ht"},{"value":"Pòm kajou se yon fwi.","name":"Haitian","natural":"Kreyòl ayisyen","classification":"ht"},{"value":"7 avril se katrevendisètyèm jou lane nan almanak gregoryen.","name":"Haitian","natural":"Kreyòl ayisyen","classification":"ht"},{"value":"* 1803 Tousen Louvèti, militè ayisyen","name":"Haitian","natural":"Kreyòl ayisyen","classification":"ht"},{"value":"1984 se 1984 m ane nan almanak gregoryen. Gade osi nonm 1984.","name":"Haitian","natural":"Kreyòl ayisyen","classification":"ht"},{"value":"764 se yon nonm. Pou ekri li, yo itilize chif arab yo.","name":"Haitian","natural":"Kreyòl ayisyen","classification":"ht"},{"value":"Se nonm antye natirèl ant 763 ak 765 nan sistèm desimal.","name":"Haitian","natural":"Kreyòl ayisyen","classification":"ht"},{"value":"394 se 439 m ane nan almanak jilyen. Gade osi nonm 394.","name":"Haitian","natural":"Kreyòl ayisyen","classification":"ht"},{"value":"996 se 1041 m ane nan almanak jilyen. Gade osi nonm 996.","name":"Haitian","natural":"Kreyòl ayisyen","classification":"ht"},{"value":"Abi, Itilize pouvwa, fòs sou yon lòt ki pa gen defans. Move aksyon yon patwon sou anplwaye li.","name":"Haitian","natural":"Kreyòl ayisyen","classification":"ht"},{"value":"Istwa mo sa","name":"Haitian","natural":"Kreyòl ayisyen","classification":"ht"},{"value":"Papa se yon paran mal.","name":"Haitian","natural":"Kreyòl ayisyen","classification":"ht"},{"value":"Papa se yon mo ti moun, tankou nan lang franse a papa.","name":"Haitian","natural":"Kreyòl ayisyen","classification":"ht"},{"value":"Se yon pwovèb, yon ekspresyon kreyòl. Sa li vle di :","name":"Haitian","natural":"Kreyòl ayisyen","classification":"ht"},{"value":"Istwa ekspresyon sa a","name":"Haitian","natural":"Kreyòl ayisyen","classification":"ht"},{"value":"Nou ap twouve nan lòt lang yo :*(fr) Franse :","name":"Haitian","natural":"Kreyòl ayisyen","classification":"ht"},{"value":"Kèk referans sou li ...","name":"Haitian","natural":"Kreyòl ayisyen","classification":"ht"},{"value":" se yon Ayisyen . Li se yon atis, mizisyen kreyòl. Li ap jwe mizik sa : ? Li ap jwe nan gwoup sa : ?","name":"Haitian","natural":"Kreyòl ayisyen","classification":"ht"},{"value":"*Dat enpòtan yo","name":"Haitian","natural":"Kreyòl ayisyen","classification":"ht"},{"value":"*Sa li fè","name":"Haitian","natural":"Kreyòl ayisyen","classification":"ht"},{"value":"*Referans pou konnen plis anlè moun sa a","name":"Haitian","natural":"Kreyòl ayisyen","classification":"ht"},{"value":"Alexander Kronrod se yon matematisyen ris, nan peyi Risi.","name":"Haitian","natural":"Kreyòl ayisyen","classification":"ht"},{"value":"*Dat enpòtan yo","name":"Haitian","natural":"Kreyòl ayisyen","classification":"ht"},{"value":"*Sa li fè, piblikasyon li nan domèn konesans matematik li","name":"Haitian","natural":"Kreyòl ayisyen","classification":"ht"},{"value":"*Referans pou konnen plis anlè moun sa a","name":"Haitian","natural":"Kreyòl ayisyen","classification":"ht"},{"value":" se yon matematisyen ris, nan peyi Risi.","name":"Haitian","natural":"Kreyòl ayisyen","classification":"ht"},{"value":"*Dat enpòtan yo","name":"Haitian","natural":"Kreyòl ayisyen","classification":"ht"},{"value":"*Sa li fè, piblikasyon li nan domèn konesans matematik li","name":"Haitian","natural":"Kreyòl ayisyen","classification":"ht"},{"value":"*Referans pou konnen plis anlè moun sa a","name":"Haitian","natural":"Kreyòl ayisyen","classification":"ht"},{"value":" se yon fizisyen alman, nan peyi Almay . Dat li yo : ( 2016–1905 ) .","name":"Haitian","natural":"Kreyòl ayisyen","classification":"ht"},{"value":"*Dat enpòtan yo","name":"Haitian","natural":"Kreyòl ayisyen","classification":"ht"},{"value":"*Sa li fè, piblikasyon li nan domèn konesans fizik li","name":"Haitian","natural":"Kreyòl ayisyen","classification":"ht"},{"value":"*Referans pou konnen plis anlè moun sa a","name":"Haitian","natural":"Kreyòl ayisyen","classification":"ht"},{"value":"Albanchez se yon komin nan pwovens Almería, nan kominote otonòm Andalouzi, nan peyi Espay.","name":"Haitian","natural":"Kreyòl ayisyen","classification":"ht"},{"value":"Istwa","name":"Haitian","natural":"Kreyòl ayisyen","classification":"ht"},{"value":" se yon komin nan pwovens Huelva, nan kominote otonòm Andalouzi, nan peyi Espay.","name":"Haitian","natural":"Kreyòl ayisyen","classification":"ht"},{"value":"Istwa","name":"Haitian","natural":"Kreyòl ayisyen","classification":"ht"},{"value":" se yon vil Etazini. Li sitye nan leta Connecticut. Chèf-lye li se Tolland Sipèfisi l se 33.5 km^2. Nan lane 2005, li te genyen 6,216 abitan, nan rejyon .","name":"Haitian","natural":"Kreyòl ayisyen","classification":"ht"},{"value":"Istwa","name":"Haitian","natural":"Kreyòl ayisyen","classification":"ht"},{"value":" se yon vil Etazini. Li sitye nan leta Ilinwa. Chèf-lye li se ? .","name":"Haitian","natural":"Kreyòl ayisyen","classification":"ht"},{"value":"Istwa","name":"Haitian","natural":"Kreyòl ayisyen","classification":"ht"},{"value":" se yon vil Etazini. Li sitye nan leta Kansas. Chèf-lye li se ? Nan lane 2004, popilasyon l te konte 10,650 moun. Lòt lane yo te genyen : 2003 (10,360),","name":"Haitian","natural":"Kreyòl ayisyen","classification":"ht"},{"value":"Istwa","name":"Haitian","natural":"Kreyòl ayisyen","classification":"ht"},{"value":" se yon vil Etazini. Li sitye nan leta Kentucky. Chèf-lye li se ?.","name":"Haitian","natural":"Kreyòl ayisyen","classification":"ht"},{"value":"Istwa","name":"Haitian","natural":"Kreyòl ayisyen","classification":"ht"},{"value":" se yon vil Etazini. Li sitye nan leta Massachusetts. Chèf-lye li se York.","name":"Haitian","natural":"Kreyòl ayisyen","classification":"ht"},{"value":"Istwa","name":"Haitian","natural":"Kreyòl ayisyen","classification":"ht"},{"value":"Sullivan  se yon vil nan eta  Nou yòk (New York) . Li nan konte, rejyon Madison .","name":"Haitian","natural":"Kreyòl ayisyen","classification":"ht"},{"value":"Istwa","name":"Haitian","natural":"Kreyòl ayisyen","classification":"ht"},{"value":"*Kominote Ayisyen, relasyon ant eta sa epi Ayiti","name":"Haitian","natural":"Kreyòl ayisyen","classification":"ht"},{"value":"Macksburg  se yon vil nan eta  Ohio, nan Etazini. Popilasyon l nan lane 2000 te genyen 202   moun. Li nan konte, rejyon   Washington .","name":"Haitian","natural":"Kreyòl ayisyen","classification":"ht"},{"value":"Istwa","name":"Haitian","natural":"Kreyòl ayisyen","classification":"ht"},{"value":"*Kominote Ayisyen, relasyon ant eta sa epi Ayiti","name":"Haitian","natural":"Kreyòl ayisyen","classification":"ht"},{"value":"Okay se yon vil nan eta Oklahoma, nan Etazini.","name":"Haitian","natural":"Kreyòl ayisyen","classification":"ht"},{"value":"Istwa","name":"Haitian","natural":"Kreyòl ayisyen","classification":"ht"},{"value":"*Kominote Ayisyen, relasyon ant eta sa epi Ayiti","name":"Haitian","natural":"Kreyòl ayisyen","classification":"ht"},{"value":"Jackson se yon vil nan eta Tennessee, nan Etazini. Li nan konte, rejyon Madison. Nan lane 2000, popilasyon l te genyen 59,643 moun.","name":"Haitian","natural":"Kreyòl ayisyen","classification":"ht"},{"value":"Istwa","name":"Haitian","natural":"Kreyòl ayisyen","classification":"ht"},{"value":"*Kominote Ayisyen, relasyon ant eta sa epi Ayiti","name":"Haitian","natural":"Kreyòl ayisyen","classification":"ht"},{"value":"Santa Monica se yon vil nan eta Texas, nan Etazini. Nan lane 2000 li te genyen 78 moun.","name":"Haitian","natural":"Kreyòl ayisyen","classification":"ht"},{"value":"Istwa","name":"Haitian","natural":"Kreyòl ayisyen","classification":"ht"},{"value":"*Kominote Ayisyen, relasyon ant eta sa epi Ayiti","name":"Haitian","natural":"Kreyòl ayisyen","classification":"ht"},{"value":"Val Verda se yon vil nan eta Utah, nan Etazini.","name":"Haitian","natural":"Kreyòl ayisyen","classification":"ht"},{"value":"Istwa","name":"Haitian","natural":"Kreyòl ayisyen","classification":"ht"},{"value":"*Kominote Ayisyen, relasyon ant eta sa epi Ayiti","name":"Haitian","natural":"Kreyòl ayisyen","classification":"ht"},{"value":"Middleburg se yon vil nan eta Vijini, nan Etazini. Li nan konte, rejyon Loudoun.","name":"Haitian","natural":"Kreyòl ayisyen","classification":"ht"},{"value":"Istwa","name":"Haitian","natural":"Kreyòl ayisyen","classification":"ht"},{"value":"*Kominote Ayisyen, relasyon ant eta sa epi Ayiti","name":"Haitian","natural":"Kreyòl ayisyen","classification":"ht"},{"value":"El Diamante se yon vil nan pwovens Guantanamo, nan peyi Kiba. Li genyen kèk 4396 moun.","name":"Haitian","natural":"Kreyòl ayisyen","classification":"ht"},{"value":"Istwa","name":"Haitian","natural":"Kreyòl ayisyen","classification":"ht"},{"value":"Ant Kiba e Ayiti genyen 90 km lanmè. Kreyòl ayisyen se dezyèm lang ki pale nan Kiba, lang ayisyen an gen menm yon estasyon radyo pou kò l.","name":"Haitian","natural":"Kreyòl ayisyen","classification":"ht"},{"value":"Gade : Tout gwo vil yo nan kat sa","name":"Haitian","natural":"Kreyòl ayisyen","classification":"ht"},{"value":"Moun sa yo se pèsonalite nan pwovens sa, men non yo rele :","name":"Haitian","natural":"Kreyòl ayisyen","classification":"ht"},{"value":"La Plazuela se yon vil nan pwovens Holguin, nan peyi Kiba. Li genyen kèk 10446 moun.","name":"Haitian","natural":"Kreyòl ayisyen","classification":"ht"},{"value":"Istwa","name":"Haitian","natural":"Kreyòl ayisyen","classification":"ht"},{"value":"Ant Kiba e Ayiti genyen 90 km lanmè. Kreyòl ayisyen se dezyèm lang ki pale nan Kiba, lang ayisyen an gen menm yon estasyon radyo pou kò l.","name":"Haitian","natural":"Kreyòl ayisyen","classification":"ht"},{"value":"Gade : Tout gwo vil yo nan kat sa","name":"Haitian","natural":"Kreyòl ayisyen","classification":"ht"},{"value":"Moun sa yo se pèsonalite nan pwovens sa, men non yo rele :","name":"Haitian","natural":"Kreyòl ayisyen","classification":"ht"},{"value":"Casa Dupont se yon vil nan pwovens Matanzas, nan peyi Kiba. Li genyen kèk 3398 moun. Detay jewografik :","name":"Haitian","natural":"Kreyòl ayisyen","classification":"ht"},{"value":"Istwa","name":"Haitian","natural":"Kreyòl ayisyen","classification":"ht"},{"value":"Kreyòl ayisyen se dezyèm lang ki pale nan Kiba, lang ayisyen an gen menm yon estasyon radyo pou kò l.","name":"Haitian","natural":"Kreyòl ayisyen","classification":"ht"},{"value":"* FallInGrain, vil ak estatistik Gade : Tout gwo vil yo nan pwovens sa nan kat sa","name":"Haitian","natural":"Kreyòl ayisyen","classification":"ht"},{"value":"Moun sa yo se pèsonalite nan pwovens sa, men non yo rele :","name":"Haitian","natural":"Kreyòl ayisyen","classification":"ht"},{"value":"Maria se yon vil nan pwovens Matanzas, nan peyi Kiba. Li genyen kèk 4394 moun. Detay jewografik :","name":"Haitian","natural":"Kreyòl ayisyen","classification":"ht"},{"value":"Istwa","name":"Haitian","natural":"Kreyòl ayisyen","classification":"ht"},{"value":"Kreyòl ayisyen se dezyèm lang ki pale nan Kiba, lang ayisyen an gen menm yon estasyon radyo pou kò l.","name":"Haitian","natural":"Kreyòl ayisyen","classification":"ht"},{"value":"* FallInGrain, vil ak estatistik Gade : Tout gwo vil yo nan pwovens sa nan kat sa","name":"Haitian","natural":"Kreyòl ayisyen","classification":"ht"},{"value":"Moun sa yo se pèsonalite nan pwovens sa, men non yo rele :","name":"Haitian","natural":"Kreyòl ayisyen","classification":"ht"},{"value":"Mèt se yon moun ki posede yon bagay. Propriyetè.","name":"Haitian","natural":"Kreyòl ayisyen","classification":"ht"},{"value":"Istwa mo sa","name":"Haitian","natural":"Kreyòl ayisyen","classification":"ht"},{"value":"== Zèv li yo ==","name":"Haitian","natural":"Kreyòl ayisyen","classification":"ht"},{"value":"<references />","name":"Haitian","natural":"Kreyòl ayisyen","classification":"ht"},{"value":"265 se 310 m ane nan almanak jilyen. Gade osi nonm 265.","name":"Haitian","natural":"Kreyòl ayisyen","classification":"ht"},{"value":"692 se 737 m ane nan almanak jilyen. Gade osi nonm 692.","name":"Haitian","natural":"Kreyòl ayisyen","classification":"ht"},{"value":"Kakile se fè operasyon matematik. Abilite pou jwenn rezilta pwoblèm. Analize. chache lide nan memwa pou mete nan reyalite tankou ekri ou byen pale.","name":"Haitian","natural":"Kreyòl ayisyen","classification":"ht"},{"value":"Istwa mo sa","name":"Haitian","natural":"Kreyòl ayisyen","classification":"ht"},{"value":"Make, Fè mak yon kote, sou yon bagay. Eseye pou pran yon boul nan men jwè yon lòt ekip. Anpeche jwè yon lòt ekip ale fè gòl. Sonje yon bagay mal yon moun fè e kontinye siveye moun sa pou wè si li ap fè menm bagay la ankò.","name":"Haitian","natural":"Kreyòl ayisyen","classification":"ht"},{"value":"Istwa mo sa","name":"Haitian","natural":"Kreyòl ayisyen","classification":"ht"},{"value":"Teleco, Premye e sèl konpayi telefòn nan peyi Ayiti pandan anpil ane pou jis lè kèk ti konpayi kòmanse rantre nan peyi a, nan finisman ane katreven-dis yo. Konpayi sa a te gen monopòl tele-kominikasyon nan peyi a e li pate kapab reponn a bezwen telefòn moun nan peyi a.","name":"Haitian","natural":"Kreyòl ayisyen","classification":"ht"},{"value":"Istwa mo sa","name":"Haitian","natural":"Kreyòl ayisyen","classification":"ht"},{"value":" se yon Ayisyen . Li se yon atis, mizisyen kreyòl. Li ap jwe mizik sa : konpa Li ap jwe nan gwoup sa : ?","name":"Haitian","natural":"Kreyòl ayisyen","classification":"ht"},{"value":"*Dat enpòtan yo","name":"Haitian","natural":"Kreyòl ayisyen","classification":"ht"},{"value":"*Sa li fè","name":"Haitian","natural":"Kreyòl ayisyen","classification":"ht"},{"value":"*Referans pou konnen plis anlè moun sa a","name":"Haitian","natural":"Kreyòl ayisyen","classification":"ht"},{"value":"Ernest Esclangon (1876-1954) se yon matematisyen ak astwnom franse.","name":"Haitian","natural":"Kreyòl ayisyen","classification":"ht"},{"value":"*Dat enpòtan yo","name":"Haitian","natural":"Kreyòl ayisyen","classification":"ht"},{"value":"*Sa li fè, piblikasyon li nan domèn konesans matematik li","name":"Haitian","natural":"Kreyòl ayisyen","classification":"ht"},{"value":"*Referans pou konnen plis anlè moun sa a","name":"Haitian","natural":"Kreyòl ayisyen","classification":"ht"},{"value":" se yon komin nan pwovens Huelva, nan kominote otonòm Andalouzi, nan peyi Espay.","name":"Haitian","natural":"Kreyòl ayisyen","classification":"ht"},{"value":"Istwa","name":"Haitian","natural":"Kreyòl ayisyen","classification":"ht"},{"value":" se yon vil Etazini. Li sitye nan leta Alabama. Chèf-lye li se Saint Clair .","name":"Haitian","natural":"Kreyòl ayisyen","classification":"ht"},{"value":"Istwa","name":"Haitian","natural":"Kreyòl ayisyen","classification":"ht"},{"value":" se yon vil Etazini. Li sitye nan leta Connecticut. Chèf-lye li se Tolland Sipèfisi l se 29.8 km^2. Nan lane 2005, li te genyen 744 abitan, nan rejyon Northeastern Connecticut .","name":"Haitian","natural":"Kreyòl ayisyen","classification":"ht"},{"value":"Istwa","name":"Haitian","natural":"Kreyòl ayisyen","classification":"ht"},{"value":" se yon vil Etazini. Li sitye nan leta Florid. Chèf-lye li se ?","name":"Haitian","natural":"Kreyòl ayisyen","classification":"ht"},{"value":"Istwa","name":"Haitian","natural":"Kreyòl ayisyen","classification":"ht"},{"value":" se yon vil Etazini. Li sitye nan leta Georgie. Chèf-lye li se ?","name":"Haitian","natural":"Kreyòl ayisyen","classification":"ht"},{"value":"Istwa","name":"Haitian","natural":"Kreyòl ayisyen","classification":"ht"},{"value":" se yon vil Etazini. Li sitye nan leta Ilinwa. Chèf-lye li se ? .","name":"Haitian","natural":"Kreyòl ayisyen","classification":"ht"},{"value":"Istwa","name":"Haitian","natural":"Kreyòl ayisyen","classification":"ht"},{"value":" se yon vil Etazini. Li sitye nan leta Iowa. Chèf-lye li se ? .","name":"Haitian","natural":"Kreyòl ayisyen","classification":"ht"},{"value":"Istwa","name":"Haitian","natural":"Kreyòl ayisyen","classification":"ht"},{"value":"Brewster  se yon vil nan eta  Nebraska .","name":"Haitian","natural":"Kreyòl ayisyen","classification":"ht"},{"value":"Istwa","name":"Haitian","natural":"Kreyòl ayisyen","classification":"ht"},{"value":"*Kominote Ayisyen, relasyon ant eta sa epi Ayiti","name":"Haitian","natural":"Kreyòl ayisyen","classification":"ht"},{"value":"Douglas  se yon vil nan eta  Nebraska .","name":"Haitian","natural":"Kreyòl ayisyen","classification":"ht"},{"value":"Istwa","name":"Haitian","natural":"Kreyòl ayisyen","classification":"ht"},{"value":"*Kominote Ayisyen, relasyon ant eta sa epi Ayiti","name":"Haitian","natural":"Kreyòl ayisyen","classification":"ht"},{"value":"North Conway  se yon vil nan eta  New Hampshire .","name":"Haitian","natural":"Kreyòl ayisyen","classification":"ht"},{"value":"Istwa","name":"Haitian","natural":"Kreyòl ayisyen","classification":"ht"},{"value":"*Kominote Ayisyen, relasyon ant eta sa epi Ayiti","name":"Haitian","natural":"Kreyòl ayisyen","classification":"ht"},{"value":"Magnetic Springs  se yon vil nan eta  Ohio, nan Etazini. Popilasyon l nan lane 2000 te genyen 323   moun. Li nan konte, rejyon   Union .","name":"Haitian","natural":"Kreyòl ayisyen","classification":"ht"},{"value":"Istwa","name":"Haitian","natural":"Kreyòl ayisyen","classification":"ht"},{"value":"*Kominote Ayisyen, relasyon ant eta sa epi Ayiti","name":"Haitian","natural":"Kreyòl ayisyen","classification":"ht"},{"value":"Tarentum se yon vil nan eta Pennsilvani, nan Etazini.","name":"Haitian","natural":"Kreyòl ayisyen","classification":"ht"},{"value":"Istwa","name":"Haitian","natural":"Kreyòl ayisyen","classification":"ht"},{"value":"*Kominote Ayisyen, relasyon ant eta sa epi Ayiti","name":"Haitian","natural":"Kreyòl ayisyen","classification":"ht"},{"value":"Mart se yon vil nan eta Texas, nan Etazini. Nan lane 2000 li te genyen 2,273 moun.","name":"Haitian","natural":"Kreyòl ayisyen","classification":"ht"},{"value":"Istwa","name":"Haitian","natural":"Kreyòl ayisyen","classification":"ht"},{"value":"*Kominote Ayisyen, relasyon ant eta sa epi Ayiti","name":"Haitian","natural":"Kreyòl ayisyen","classification":"ht"},{"value":"Nazareth se yon vil nan eta Texas, nan Etazini. Nan lane 2000 li te genyen 356 moun.","name":"Haitian","natural":"Kreyòl ayisyen","classification":"ht"},{"value":"Istwa","name":"Haitian","natural":"Kreyòl ayisyen","classification":"ht"},{"value":"*Kominote Ayisyen, relasyon ant eta sa epi Ayiti","name":"Haitian","natural":"Kreyòl ayisyen","classification":"ht"},{"value":"Lavadero se yon vil nan pwovens Cienfuegos, nan peyi Kiba. Li genyen kèk 6618 moun. Detay jewografik :","name":"Haitian","natural":"Kreyòl ayisyen","classification":"ht"},{"value":"Istwa","name":"Haitian","natural":"Kreyòl ayisyen","classification":"ht"},{"value":"Ant Kiba e Ayiti genyen 90 km lanmè. Kreyòl ayisyen se dezyèm lang ki pale nan Kiba, lang ayisyen an gen menm yon estasyon radyo pou kò l.","name":"Haitian","natural":"Kreyòl ayisyen","classification":"ht"},{"value":"Gade : Tout gwo vil yo nan kat sa","name":"Haitian","natural":"Kreyòl ayisyen","classification":"ht"},{"value":"Moun sa yo se pèsonalite nan pwovens sa, men non yo rele :","name":"Haitian","natural":"Kreyòl ayisyen","classification":"ht"},{"value":"Gobiro se yon vil nan pwovens Granma, nan peyi Kiba. Li genyen kèk 9623 moun.","name":"Haitian","natural":"Kreyòl ayisyen","classification":"ht"},{"value":"Istwa","name":"Haitian","natural":"Kreyòl ayisyen","classification":"ht"},{"value":"Ant Kiba e Ayiti genyen 90 km lanmè. Kreyòl ayisyen se dezyèm lang ki pale nan Kiba, lang ayisyen an gen menm yon estasyon radyo pou kò l.","name":"Haitian","natural":"Kreyòl ayisyen","classification":"ht"},{"value":"Gade : Tout gwo vil yo nan kat sa","name":"Haitian","natural":"Kreyòl ayisyen","classification":"ht"},{"value":"Moun sa yo se pèsonalite nan pwovens sa, men non yo rele :","name":"Haitian","natural":"Kreyòl ayisyen","classification":"ht"},{"value":"El Flete se yon vil nan pwovens Habana, nan peyi Kiba. Li genyen kèk 19516 moun.","name":"Haitian","natural":"Kreyòl ayisyen","classification":"ht"},{"value":"Istwa","name":"Haitian","natural":"Kreyòl ayisyen","classification":"ht"},{"value":"Ant Kiba e Ayiti genyen 90 km lanmè. Kreyòl ayisyen se dezyèm lang ki pale nan Kiba, lang ayisyen an gen menm yon estasyon radyo pou kò l.","name":"Haitian","natural":"Kreyòl ayisyen","classification":"ht"},{"value":"Gade : Tout gwo vil yo nan kat sa","name":"Haitian","natural":"Kreyòl ayisyen","classification":"ht"},{"value":"Moun sa yo se pèsonalite nan pwovens sa, men non yo rele :","name":"Haitian","natural":"Kreyòl ayisyen","classification":"ht"},{"value":"La Salud se yon vil nan pwovens Habana, nan peyi Kiba. Li genyen kèk 23949 moun.","name":"Haitian","natural":"Kreyòl ayisyen","classification":"ht"},{"value":"Istwa","name":"Haitian","natural":"Kreyòl ayisyen","classification":"ht"},{"value":"Ant Kiba e Ayiti genyen 90 km lanmè. Kreyòl ayisyen se dezyèm lang ki pale nan Kiba, lang ayisyen an gen menm yon estasyon radyo pou kò l.","name":"Haitian","natural":"Kreyòl ayisyen","classification":"ht"},{"value":"Gade : Tout gwo vil yo nan kat sa","name":"Haitian","natural":"Kreyòl ayisyen","classification":"ht"},{"value":"Moun sa yo se pèsonalite nan pwovens sa, men non yo rele :","name":"Haitian","natural":"Kreyòl ayisyen","classification":"ht"},{"value":"Aguas Blancas se yon vil nan pwovens Las Tunas, nan peyi Kiba. Li genyen kèk 14309 moun.","name":"Haitian","natural":"Kreyòl ayisyen","classification":"ht"},{"value":"Istwa","name":"Haitian","natural":"Kreyòl ayisyen","classification":"ht"},{"value":"Ant Kiba e Ayiti genyen 90 km lanmè. Kreyòl ayisyen se dezyèm lang ki pale nan Kiba, lang ayisyen an gen menm yon estasyon radyo pou kò l.","name":"Haitian","natural":"Kreyòl ayisyen","classification":"ht"},{"value":"Gade : Tout gwo vil yo nan kat sa","name":"Haitian","natural":"Kreyòl ayisyen","classification":"ht"},{"value":"Moun sa yo se pèsonalite nan pwovens sa, men non yo rele :","name":"Haitian","natural":"Kreyòl ayisyen","classification":"ht"},{"value":"La Esperanza se yon vil nan pwovens Sancti Spiritus, nan peyi Kiba. Li genyen kèk 9811 moun.","name":"Haitian","natural":"Kreyòl ayisyen","classification":"ht"},{"value":"Istwa","name":"Haitian","natural":"Kreyòl ayisyen","classification":"ht"},{"value":"Ant Kiba e Ayiti genyen 90 km lanmè. Kreyòl ayisyen se dezyèm lang ki pale nan Kiba, lang ayisyen an gen menm yon estasyon radyo pou kò l.","name":"Haitian","natural":"Kreyòl ayisyen","classification":"ht"},{"value":"Gade : Tout gwo vil yo nan kat sa","name":"Haitian","natural":"Kreyòl ayisyen","classification":"ht"},{"value":"Moun sa yo se pèsonalite nan pwovens sa, men non yo rele :","name":"Haitian","natural":"Kreyòl ayisyen","classification":"ht"},{"value":"Pajarito se yon vil nan pwovens Pinar del Rio, nan peyi Kiba. Li genyen kèk 5162 moun. Detay jewografik :","name":"Haitian","natural":"Kreyòl ayisyen","classification":"ht"},{"value":"Istwa","name":"Haitian","natural":"Kreyòl ayisyen","classification":"ht"},{"value":"Kreyòl ayisyen se dezyèm lang ki pale nan Kiba, lang ayisyen an gen menm yon estasyon radyo pou kò l.","name":"Haitian","natural":"Kreyòl ayisyen","classification":"ht"},{"value":"* FallInGrain, vil ak estatistik Gade : Tout gwo vil yo nan pwovens sa nan kat sa","name":"Haitian","natural":"Kreyòl ayisyen","classification":"ht"},{"value":"Moun sa yo se pèsonalite nan pwovens sa, men non yo rele :","name":"Haitian","natural":"Kreyòl ayisyen","classification":"ht"},{"value":"Punto San Juan se yon vil nan pwovens Camaguey, nan peyi Kiba. Li genyen kèk 6486 moun. Detay jewografik :","name":"Haitian","natural":"Kreyòl ayisyen","classification":"ht"},{"value":"Istwa","name":"Haitian","natural":"Kreyòl ayisyen","classification":"ht"},{"value":"Kreyòl ayisyen se dezyèm lang ki pale nan Kiba, lang ayisyen an gen menm yon estasyon radyo pou kò l.","name":"Haitian","natural":"Kreyòl ayisyen","classification":"ht"},{"value":"* FallInGrain, vil ak estatistik Gade : Tout gwo vil yo nan pwovens sa nan kat sa","name":"Haitian","natural":"Kreyòl ayisyen","classification":"ht"},{"value":"Moun sa yo se pèsonalite nan pwovens sa, men non yo rele :","name":"Haitian","natural":"Kreyòl ayisyen","classification":"ht"},{"value":"Ròl se pa pou yon moun nan teyat oubyen nan lavi.","name":"Haitian","natural":"Kreyòl ayisyen","classification":"ht"},{"value":"Istwa mo sa","name":"Haitian","natural":"Kreyòl ayisyen","classification":"ht"},{"value":"Rapò optik se yon kantite ki reprezante agrandisman oswa rediksyon imaj nan gwosè, parapò ak objè a.","name":"Haitian","natural":"Kreyòl ayisyen","classification":"ht"},{"value":"300 se yon nonm. Pou ekri li, yo itilize chif arab yo.","name":"Haitian","natural":"Kreyòl ayisyen","classification":"ht"},{"value":"Se nonm antye natirèl ant 299 ak 301 nan sistèm desimal.","name":"Haitian","natural":"Kreyòl ayisyen","classification":"ht"},{"value":"934 se 979 m ane nan almanak jilyen. Gade osi nonm 934.","name":"Haitian","natural":"Kreyòl ayisyen","classification":"ht"},{"value":" se yon ekriven. Li ekri liv konsène Ayiti oubyen kreyòl ayisyen oubyen nan karayib an.","name":"Haitian","natural":"Kreyòl ayisyen","classification":"ht"},{"value":"*Dat enpòtan yo","name":"Haitian","natural":"Kreyòl ayisyen","classification":"ht"},{"value":"* Haïtiana bibliographie haïtienne","name":"Haitian","natural":"Kreyòl ayisyen","classification":"ht"},{"value":"*Referans pou konnen plis anlè moun sa a","name":"Haitian","natural":"Kreyòl ayisyen","classification":"ht"},{"value":" se yon ekriven.","name":"Haitian","natural":"Kreyòl ayisyen","classification":"ht"},{"value":"*Dat enpòtan yo","name":"Haitian","natural":"Kreyòl ayisyen","classification":"ht"},{"value":"*Referans pou konnen plis anlè moun sa a","name":"Haitian","natural":"Kreyòl ayisyen","classification":"ht"},{"value":"Jean Joseph Duval se yon atis, yon pent ayisyen.","name":"Haitian","natural":"Kreyòl ayisyen","classification":"ht"},{"value":"*Dat enpòtan yo","name":"Haitian","natural":"Kreyòl ayisyen","classification":"ht"},{"value":"*Sa li fè","name":"Haitian","natural":"Kreyòl ayisyen","classification":"ht"},{"value":"*[http://www.webster.edu/~corbetre/haiti/art/artist-list.html Yon lis atis pent ayisyen ak byografi] *kèk lyen ...","name":"Haitian","natural":"Kreyòl ayisyen","classification":"ht"},{"value":"Hilome Jose se yon atis, yon pent ayisyen.","name":"Haitian","natural":"Kreyòl ayisyen","classification":"ht"},{"value":"*Dat enpòtan yo","name":"Haitian","natural":"Kreyòl ayisyen","classification":"ht"},{"value":"*Sa li fè","name":"Haitian","natural":"Kreyòl ayisyen","classification":"ht"},{"value":"*[http://www.webster.edu/~corbetre/haiti/art/artist-list.html Yon lis atis pent ayisyen ak byografi] *kèk lyen ...","name":"Haitian","natural":"Kreyòl ayisyen","classification":"ht"},{"value":" se yon matematisyen nan dyaspora afriken.","name":"Haitian","natural":"Kreyòl ayisyen","classification":"ht"},{"value":"*Dat enpòtan yo","name":"Haitian","natural":"Kreyòl ayisyen","classification":"ht"},{"value":"*Sa li fè, piblikasyon li nan domèn konesans matematik li","name":"Haitian","natural":"Kreyòl ayisyen","classification":"ht"},{"value":"*Referans pou konnen plis anlè moun sa a","name":"Haitian","natural":"Kreyòl ayisyen","classification":"ht"}]}