{"lines":[{"value":"ബ്രൂണൈൻ സുൽത്താൻ ഒമർ അലി സൈഫുദ്ദീൻ II ൽ നിന്ന്ബ്രൂണൈയുടെ തെക്കുപടിഞ്ഞാറൻ പ്രദേശത്ത് 1841 ൽ ജെയിംസ് ബ്രൂക്കിനു ഭൂമിക്ക് ലഭിക്കുന്നതുവരെ സാരവാക്ക് ബ്രുണായിയുടെ ഭാഗമായിരുന്നു. അദ്ദേഹം പിന്നീട് ഈ പ്രദേശത്തിന്റെ രാജാ എന്ന സ്ഥാനപ്പേര് സ്ഥിരീകരിച്ചു. ബോർണിയോ ദ്വീപിലെ വടക്കുഭാഗത്തെ ഭൂരിഭാഗവും പിടിച്ചടക്കിയ ആദ്യത്തെ രണ്ട് വെള്ളരാജന്മാരുടെ ഭരണകാലത്ത് സരാവക് രാജ്യം വികസിക്കുകയും വിപുലീകരിക്കുകയും ചെയ്തു. ബ്രൂക്ക് ഭരണകൂടങ്ങൾ ബ്രൂണൈയിൽ നിന്ന് കൂടുതൽ ഭൂമിയെ പാട്ടത്തിന് കൊടുക്കുകയോ അല്ലെങ്കിൽ കൂട്ടിച്ചേർക്കുകയോ ചെയ്തു.ലഘുചിത്രം|Graves of the White Rajahs at St Leonard's Church, Sheepstor, Devon, England.","sentiment":"ml","name":"Malayalam","natural":"മലയാളം"},{"value":"ലഘുചിത്രം|320x320ബിന്ദു|മരിച്ച സൈറസിന്റെ ശിരസ്സ് രക്തം നിറച്ച പാത്രത്തിൽ മുക്കുന്ന തോമിരിസ്","sentiment":"ml","name":"Malayalam","natural":"മലയാളം"},{"value":"[[പ്രമാണം:Preti,_Mattia_-_Queen_Tomyris_Receiving_the_Head_of_Cyrus,_King_of_Persia_-_1670-72.jpg|ഇടത്ത്‌|ലഘുചിത്രം|സൈറസ്സിന്റെ ശിരസ്സ് ഏറ്റുവാങ്ങുന്ന തോമിറിസ്]] പേർഷ്യൻ ഭരണാധികാരിയും അക്കീമെനിഡ് സാമ്രാജ്യത്തിന്റെ സ്ഥാപകനുമായിരുന്ന മഹാനായ സൈറസി നെ വധിച്ചത് തോമിറിസ് ആണെന്ന് നിരവധി ചരിത്രകാരന്മാർ രേഖപ്പെടുത്തിയിട്ടുണ്ട്. ഏതാണ്ട് നൂറുവർഷത്തിനു ശേഷം ബി.സി. 484 നും 425 നും മദ്ധ്യേ ജീവിച്ചിരുന്ന  ഹെറോഡോട്ടസ് അവരെക്കുറിച്ച് എഴുതുകയുണ്ടായി. De origine actibusque Getarum (\"The origin and deeds of the Goths/Getae\") എന്ന ചരിത്രസംഹിതയിൽ സ്ട്രാബോ, പോളിയേനസ്, കാസിയോഡോറസ്, ജോർഡെയ്ൻസ് എന്നിവരും തോമിറിസിന്റെ പോരാട്ടവീര്യം പരാമർശിച്ചിട്ടുണ്ട്.","sentiment":"ml","name":"Malayalam","natural":"മലയാളം"},{"value":"ലഘുചിത്രം|317x317ബിന്ദു|തോമിറിസ്- 15ആം നൂറ്റാണ്ടിലെ കാസ്റ്റഗ്നോ എന്ന ചിത്രകാരന്റെ ഭാവനയിൽ Eustache Deschamps എന്ന കവി അദ്ദേഹത്തിന്റെ കവിതയിൽ ഒമ്പത് ഉത്തമസ്ത്രീകളിൽ ഒരാളായി തോമിറിസിനെ ഷെയ്ക്സ്പിയറുടെ ആദ്യകാല നാടകമായ കിങ് ഹെൻറി VI ൽ, ഒന്നാം ഭാഗത്തിൽ, താൽബോട്ട് പ്രഭുവിന്റെ ആഗമനത്തിൽ ഔറനിലെ പ്രഭ്വി ഈ വരികൾ പറയുന്നുണ്ട്: The plot is laid: if all things fall out right, I shall as famous be by this exploit As Scythian Tomyris by Cyrus' death.","sentiment":"ml","name":"Malayalam","natural":"മലയാളം"},{"value":"തോംറിസ് അല്ലെങ്കിൽ തോമറിസ് എന്ന പേരു മദ്ധ്യേഷ്യയിലും തുർക്കിയിലും കൂടുതൽ പ്രചാരത്തിൽ വന്നത് ഇരുപത്-ഇരുപത്തൊന്നാം നൂറ്റാണ്ടുകൾക്കിടയിലാണ്. ഉസ്ബെക്ക് എഴുത്തുകാരനായ ക്സുർഷിദ് ഡേവറോൺ 1984 ൽ പുറത്തിറക്കിയ Toʻmarisning Koʻzlari (The Eyes of Tomyris) എന്ന കഥ-കവിത സമാഹാരത്തിലും ഈ പേരു പറയുന്നുണ്ട്. അതുപോലെ മറ്റൊരു ഉസ്ബെക്ക് കവിയായ ഹലിമ ക്സുദോയ്ബെർദിയേവ രചിച്ച Toʻmarisning Aytgani (The Sayings of Tomyris) എന്ന കവിതാപുസ്തകത്തിലും തോമിറിസിനെ പറ്റി പറയുന്നു.","sentiment":"ml","name":"Malayalam","natural":"മലയാളം"},{"value":"* Alyssa Miller at the Sports Illustrated Swimsuit Issue","sentiment":"ml","name":"Malayalam","natural":"മലയാളം"}]}